qoalai
