Metadata-Version: 2.1
Name: qoalai
Version: 0.4.17
Summary: qoala.id data science team library
Home-page: UNKNOWN
Author: qoala ai team
License: UNKNOWN
Platform: UNKNOWN
